{
   "packages":[
      {
         "name":"TimmehTimmeh",
         "maintainer":"TimmehTimmeh ",
         "websiteURL":"https://www.TimmehTimmeh.com",
         "email":"TechSupport@TimmehTimmeh.com",
         "help":{
            "online":"https://forum.TimmehTimmeh.com"
         },
         "platforms":[
            {
               "name":"TimmehTimmeh AVR Boards",
               "architecture":"avr",
               "version":"0.0.1",
               "category":"Contributed",
               "url":"https://github.com/TimmehTimmeh/Arduino_Boards/raw/master/IDE_Board_Manager/TimmehTimmehboards.0.0.1.tar.bz2",
               "archiveFileName":"TimmehTimmehboards.1.1.5.tar.bz2",
               "checksum":"SHA-256:7ed792ec89b22521c132e77670ebeceebebffdaacf3106afd105ed3203d50533",
               "size":"1162215",
               "help":{
                  "online":"https://monkeys.TimmehTimmeh.com"
               },
               "boards":[
                  {
                    "name":"ReflowBoard"
                  }
               ],
               "toolsDependencies":[
                  {
                     "packager":"arduino",
                     "name":"avr-gcc",
                     "version":"4.8.1-arduino5"
                  },
                  {
                     "packager":"arduino",
                     "name":"avrdude",
                     "version":"6.0.1-arduino5"
                  }
               ]
            }
         ],
         "tools":[]
      }
   ]
}
